{
  "outbounds": [
    {
      "type": "selector",
      "tag": "Proxy",
      "outbounds": [
        "💦 1 - VLESS - Domain",
        "💦 2 - VLESS - Domain",
        "💦 3 - VLESS - IPv4",
        "💦 4 - VLESS - IPv4",
        "💦 5 - VLESS - Domain",
        "💦 6 - VLESS - Domain",
        "💦 7 - VLESS - IPv4",
        "💦 8 - VLESS - IPv4"
      ]
    },
    {
      "tag": "💦 1 - VLESS - Domain",
      "type": "vless",
      "server": "162.159.135.43",
      "server_port": 443,
      "uuid": "11566ad8-9fb9-4f0e-b58a-cf8d02be15c7",
      "packet_encoding": "xudp",
      "transport": {
        "type": "ws",
        "path": "/eyJqdW5rIjoiNnE5NkJEaUF6IiwicHJvdG9jb2wiOiJ2bCIsIm1vZGUiOiJwcm94eWlwIiwicGFuZWxJUHMiOltdfQ==",
        "headers": { "Host": "qqq.tzm-99.x10.mx" }
      },
      "tls": { "enabled": true, "server_name": "QqQ.tZm-99.x10.MX", "utls": { "enabled": true, "fingerprint": "chrome" } }
    },
    {
      "tag": "💦 2 - VLESS - Domain",
      "type": "vless",
      "server": "162.159.0.24",
      "server_port": 443,
      "uuid": "11566ad8-9fb9-4f0e-b58a-cf8d02be15c7",
      "packet_encoding": "xudp",
      "transport": {
        "type": "ws",
        "path": "/eyJqdW5rIjoieFFldkRtY2VpRyIsInByb3RvY29sIjoidmwiLCJtb2RlIjoicHJveHlpcCIsInBhbmVsSVBzIjpbXX0=",
        "headers": { "Host": "qqq.tzm-99.x10.mx" }
      },
      "tls": { "enabled": true, "server_name": "QqQ.TzM-99.x10.mX", "utls": { "enabled": true, "fingerprint": "chrome" } }
    },
    {
      "tag": "💦 3 - VLESS - IPv4",
      "type": "vless",
      "server": "104.16.8.167",
      "server_port": 443,
      "uuid": "11566ad8-9fb9-4f0e-b58a-cf8d02be15c7",
      "packet_encoding": "xudp",
      "transport": {
        "type": "ws",
        "path": "/eyJqdW5rIjoiQ2l2c3BWakNvUTNZMUZtIiwicHJvdG9jb2wiOiJ2bCIsIm1vZGUiOiJwcm94eWlwIiwicGFuZWxJUHMiOltdfQ==",
        "headers": { "Host": "qqq.tzm-99.x10.mx" }
      },
      "tls": { "enabled": true, "server_name": "qQQ.TzM-99.X10.mX", "utls": { "enabled": true, "fingerprint": "chrome" } }
    },
    {
      "tag": "💦 4 - VLESS - IPv4",
      "type": "vless",
      "server": "104.24.203.9",
      "server_port": 443,
      "uuid": "11566ad8-9fb9-4f0e-b58a-cf8d02be15c7",
      "packet_encoding": "xudp",
      "transport": {
        "type": "ws",
        "path": "/eyJqdW5rIjoib3JHUUphQWMiLCJwcm90b2NvbCI6InZsIiwibW9kZSI6InByb3h5aXAiLCJwYW5lbElQcyI6W119",
        "headers": { "Host": "qqq.tzm-99.x10.mx" }
      },
      "tls": { "enabled": true, "server_name": "qQQ.TZM-99.X10.mX", "utls": { "enabled": true, "fingerprint": "chrome" } }
    },
    {
      "tag": "💦 5 - VLESS - Domain",
      "type": "vless",
      "server": "104.16.21.161",
      "server_port": 8443,
      "uuid": "11566ad8-9fb9-4f0e-b58a-cf8d02be15c7",
      "packet_encoding": "xudp",
      "transport": {
        "type": "ws",
        "path": "/eyJqdW5rIjoiV3pTS29qN0psZFgiLCJwcm90b2NvbCI6InZsIiwibW9kZSI6InByb3h5aXAiLCJwYW5lbElQcyI6W119",
        "headers": { "Host": "qqq.tzm-99.x10.mx" }
      },
      "tls": { "enabled": true, "server_name": "QQQ.TZM-99.x10.MX", "utls": { "enabled": true, "fingerprint": "chrome" } }
    },
    {
      "tag": "💦 6 - VLESS - Domain",
      "type": "vless",
      "server": "104.19.211.38",
      "server_port": 8443,
      "uuid": "11566ad8-9fb9-4f0e-b58a-cf8d02be15c7",
      "packet_encoding": "xudp",
      "transport": {
        "type": "ws",
        "path": "/eyJqdW5rIjoiNVRINk9KVXI5YXZkZCIsInByb3RvY29sIjoidmwiLCJtb2RlIjoicHJveHlpcCIsInBhbmVsSVBzIjpbXX0=",
        "headers": { "Host": "qqq.tzm-99.x10.mx" }
      },
      "tls": { "enabled": true, "server_name": "Qqq.TzM-99.x10.mX", "utls": { "enabled": true, "fingerprint": "chrome" } }
    },
    {
      "tag": "💦 7 - VLESS - IPv4",
      "type": "vless",
      "server": "162.159.246.225",
      "server_port": 8443,
      "uuid": "11566ad8-9fb9-4f0e-b58a-cf8d02be15c7",
      "packet_encoding": "xudp",
      "transport": {
        "type": "ws",
        "path": "/eyJqdW5rIjoib1NQOGVkNk1nTVBiRHVpWCIsInByb3RvY29sIjoidmwiLCJtb2RlIjoicHJveHlpcCIsInBhbmVsSVBzIjpbXX0=",
        "headers": { "Host": "qqq.tzm-99.x10.mx" }
      },
      "tls": { "enabled": true, "server_name": "qQq.Tzm-99.X10.Mx", "utls": { "enabled": true, "fingerprint": "chrome" } }
    },
    {
      "tag": "💦 8 - VLESS - IPv4",
      "type": "vless",
      "server": "104.16.38.40",
      "server_port": 8443,
      "uuid": "11566ad8-9fb9-4f0e-b58a-cf8d02be15c7",
      "packet_encoding": "xudp",
      "transport": {
        "type": "ws",
        "path": "/eyJqdW5rIjoiM3FFTFlVcGZMNXRlYlJ0IiwicHJvdG9jb2wiOiJ2bCIsIm1vZGUiOiJwcm94eWlwIiwicGFuZWxJUHMiOltdfQ==",
        "headers": { "Host": "qqq.tzm-99.x10.mx" }
      },
      "tls": { "enabled": true, "server_name": "QqQ.Tzm-99.X10.mx", "utls": { "enabled": true, "fingerprint": "chrome" } }
    },
    { "type": "direct", "tag": "direct" },
    { "type": "dns", "tag": "dns-out" }
  ]
}
